copia/__init__.py
copia/bootstrap.py
copia/coverage.py
copia/data.py
copia/diversity.py
copia/estimators.py
copia/plot.py
copia/rarefaction_extrapolation.py
copia/simulation.py
copia/stats.py
copia/utils.py
copia-0.1.6.dist-info/licenses/LICENSE
copia-0.1.6.dist-info/METADATA
copia-0.1.6.dist-info/WHEEL
copia-0.1.6.dist-info/top_level.txt
copia-0.1.6.dist-info/RECORD
