Metadata-Version: 2.4
Name: copia
Version: 0.1.6
Summary: Add your description here
Home-page: https://github.com/mikekestemont/copia
Author: Mike Kestemont & Folgert Karsdorp
Requires-Python: >=3.13
License-File: LICENSE
Requires-Dist: matplotlib>=3.8
Requires-Dist: numpy>=1.24
Requires-Dist: pandas>=2.1
Requires-Dist: pytest>=7.4
Requires-Dist: scipy>=1.11
Requires-Dist: tqdm>=4.64
Dynamic: author
Dynamic: home-page
Dynamic: license-file
